odoo/addons/ssi_work_log_expense/README.rst
odoo/addons/ssi_work_log_expense/__init__.py
odoo/addons/ssi_work_log_expense/__manifest__.py
odoo/addons/ssi_work_log_expense/data/account_journal_data.xml
odoo/addons/ssi_work_log_expense/data/approval_template_data.xml
odoo/addons/ssi_work_log_expense/data/ir_sequence_data.xml
odoo/addons/ssi_work_log_expense/data/policy_template_data.xml
odoo/addons/ssi_work_log_expense/data/sequence_template_data.xml
odoo/addons/ssi_work_log_expense/demo/account_account_demo.xml
odoo/addons/ssi_work_log_expense/demo/account_journal_demo.xml
odoo/addons/ssi_work_log_expense/demo/work_log_expense_type_demo.xml
odoo/addons/ssi_work_log_expense/models/__init__.py
odoo/addons/ssi_work_log_expense/models/hr_work_log.py
odoo/addons/ssi_work_log_expense/models/work_log_expense.py
odoo/addons/ssi_work_log_expense/models/work_log_expense_summary.py
odoo/addons/ssi_work_log_expense/models/work_log_expense_type.py
odoo/addons/ssi_work_log_expense/security/ir.model.access.csv
odoo/addons/ssi_work_log_expense/security/ir_module_category_data.xml
odoo/addons/ssi_work_log_expense/security/ir_rule_data.xml
odoo/addons/ssi_work_log_expense/security/res_group_data.xml
odoo/addons/ssi_work_log_expense/static/description/icon.png
odoo/addons/ssi_work_log_expense/views/work_log_expense_type_views.xml
odoo/addons/ssi_work_log_expense/views/work_log_expense_views.xml
odoo/addons/ssi_work_log_expense/wizards/__init__.py
odoo/addons/ssi_work_log_expense/wizards/generate_work_log_expense.py
odoo/addons/ssi_work_log_expense/wizards/generate_work_log_expense_views.xml
odoo14_addon_ssi_work_log_expense-14.0.1.5.0.dist-info/METADATA
odoo14_addon_ssi_work_log_expense-14.0.1.5.0.dist-info/WHEEL
odoo14_addon_ssi_work_log_expense-14.0.1.5.0.dist-info/top_level.txt
odoo14_addon_ssi_work_log_expense-14.0.1.5.0.dist-info/RECORD
